{
  "video_id": "kZhIA8P6xWI",
  "segments": [
    {
      "start": 15.52,
      "end": 22.900000000000002,
      "line_idx": 3,
      "shabad_id": 4377,
      "verse_id": 52524,
      "banidb_gurmukhi": "ਸਾਧਿਕ ਸਿਧ ਸਗਲ ਮੁਨਿ ਲੋਚਹਿ ਬਿਰਲੇ ਲਾਗੈ ਧਿਆਨੁ ॥"
    },
    {
      "start": 22.900000000000002,
      "end": 30.0,
      "line_idx": 6,
      "shabad_id": 4377,
      "verse_id": 52527,
      "banidb_gurmukhi": "ਖਿਨੁ ਪਲੁ ਬਿਸਰੁ ਨਹੀ ਮੇਰੇ ਕਰਤੇ ਇਹੁ ਨਾਨਕੁ ਮਾਂਗੈ ਦਾਨੁ ॥੨॥੯੦॥੧੧੩॥"
    },
    {
      "start": 30.0,
      "end": 50.0,
      "line_idx": 6,
      "shabad_id": 4377,
      "verse_id": 52527,
      "banidb_gurmukhi": "ਖਿਨੁ ਪਲੁ ਬਿਸਰੁ ਨਹੀ ਮੇਰੇ ਕਰਤੇ ਇਹੁ ਨਾਨਕੁ ਮਾਂਗੈ ਦਾਨੁ ॥੨॥੯੦॥੧੧੩॥"
    },
    {
      "start": 50.0,
      "end": 70.0,
      "line_idx": 5,
      "shabad_id": 4377,
      "verse_id": 52526,
      "banidb_gurmukhi": "ਜਾ ਕੈ ਰਿਦੈ ਵਸੈ ਭੈ ਭੰਜਨੁ ਤਿਸੁ ਜਾਨੈ ਸਗਲ ਜਹਾਨੁ ॥"
    },
    {
      "start": 70.0,
      "end": 100.0,
      "line_idx": 1,
      "shabad_id": 4377,
      "verse_id": 52522,
      "banidb_gurmukhi": "ਪੋਥੀ ਪਰਮੇਸਰ ਕਾ ਥਾਨੁ ॥"
    },
    {
      "start": 100.0,
      "end": 120.0,
      "line_idx": 5,
      "shabad_id": 4377,
      "verse_id": 52526,
      "banidb_gurmukhi": "ਜਾ ਕੈ ਰਿਦੈ ਵਸੈ ਭੈ ਭੰਜਨੁ ਤਿਸੁ ਜਾਨੈ ਸਗਲ ਜਹਾਨੁ ॥"
    },
    {
      "start": 120.0,
      "end": 150.0,
      "line_idx": 1,
      "shabad_id": 4377,
      "verse_id": 52522,
      "banidb_gurmukhi": "ਪੋਥੀ ਪਰਮੇਸਰ ਕਾ ਥਾਨੁ ॥"
    },
    {
      "start": 150.0,
      "end": 160.0,
      "line_idx": 3,
      "shabad_id": 4377,
      "verse_id": 52524,
      "banidb_gurmukhi": "ਸਾਧਿਕ ਸਿਧ ਸਗਲ ਮੁਨਿ ਲੋਚਹਿ ਬਿਰਲੇ ਲਾਗੈ ਧਿਆਨੁ ॥"
    },
    {
      "start": 160.0,
      "end": 170.0,
      "line_idx": 5,
      "shabad_id": 4377,
      "verse_id": 52526,
      "banidb_gurmukhi": "ਜਾ ਕੈ ਰਿਦੈ ਵਸੈ ਭੈ ਭੰਜਨੁ ਤਿਸੁ ਜਾਨੈ ਸਗਲ ਜਹਾਨੁ ॥"
    },
    {
      "start": 170.0,
      "end": 180.0,
      "line_idx": 1,
      "shabad_id": 4377,
      "verse_id": 52522,
      "banidb_gurmukhi": "ਪੋਥੀ ਪਰਮੇਸਰ ਕਾ ਥਾਨੁ ॥"
    },
    {
      "start": 180.0,
      "end": 190.0,
      "line_idx": 3,
      "shabad_id": 4377,
      "verse_id": 52524,
      "banidb_gurmukhi": "ਸਾਧਿਕ ਸਿਧ ਸਗਲ ਮੁਨਿ ਲੋਚਹਿ ਬਿਰਲੇ ਲਾਗੈ ਧਿਆਨੁ ॥"
    },
    {
      "start": 190.0,
      "end": 200.0,
      "line_idx": 4,
      "shabad_id": 4377,
      "verse_id": 52525,
      "banidb_gurmukhi": "ਜਿਸਹਿ ਕ੍ਰਿਪਾਲੁ ਹੋਇ ਮੇਰਾ ਸੁਆਮੀ ਪੂਰਨ ਤਾ ਕੋ ਕਾਮੁ ॥੧॥"
    },
    {
      "start": 200.0,
      "end": 210.0,
      "line_idx": 5,
      "shabad_id": 4377,
      "verse_id": 52526,
      "banidb_gurmukhi": "ਜਾ ਕੈ ਰਿਦੈ ਵਸੈ ਭੈ ਭੰਜਨੁ ਤਿਸੁ ਜਾਨੈ ਸਗਲ ਜਹਾਨੁ ॥"
    },
    {
      "start": 210.0,
      "end": 250.0,
      "line_idx": 1,
      "shabad_id": 4377,
      "verse_id": 52522,
      "banidb_gurmukhi": "ਪੋਥੀ ਪਰਮੇਸਰ ਕਾ ਥਾਨੁ ॥"
    },
    {
      "start": 250.0,
      "end": 300.0,
      "line_idx": 5,
      "shabad_id": 4377,
      "verse_id": 52526,
      "banidb_gurmukhi": "ਜਾ ਕੈ ਰਿਦੈ ਵਸੈ ਭੈ ਭੰਜਨੁ ਤਿਸੁ ਜਾਨੈ ਸਗਲ ਜਹਾਨੁ ॥"
    },
    {
      "start": 300.0,
      "end": 306.027375,
      "line_idx": 1,
      "shabad_id": 4377,
      "verse_id": 52522,
      "banidb_gurmukhi": "ਪੋਥੀ ਪਰਮੇਸਰ ਕਾ ਥਾਨੁ ॥"
    }
  ]
}