{
  "kind": "silver_manifest_asr_eval",
  "manifest": "training_data/silver_300h_holdout/manifest.json",
  "model_id": "surindersinghssj/surt-small-v3",
  "adapter_dir": "lora_adapters/v5b_mac_diverse",
  "language": "pa",
  "min_score": 0.9,
  "limit": 100,
  "sample_strategy": "round_robin_video",
  "elapsed_s": 102.74135887506418,
  "summary": {
    "n": 100,
    "exact_norm_rate": 0.73,
    "mean_ratio": 96.27184835757552,
    "median_ratio": 100.0,
    "mean_wratio": 96.33424151996869,
    "median_wratio": 100.0,
    "total_duration_s": 741.154,
    "unique_videos": 19,
    "unique_shabads": 28
  },
  "rows": [
    {
      "idx": 0,
      "audio": "training_data/silver_300h_holdout/clips/njmuAa8IY80_clip_01678.wav",
      "video_id": "njmuAa8IY80",
      "shabad_id": "7TL",
      "duration_s": 7.601,
      "label_score": 1.0,
      "target": "ਸਫਲੁ ਹੈ ਜੇ ਕੋ ਕਰੇ ਚਿਤੁ ਲਾਇ",
      "pred": "ਸਫਲੁ ਹੈ ਜੇ ਕੋ ਕਰੇ ਚਿਤੁ ਲਾਇ",
      "norm_target": "sphlu hai jee koo kree citu laai",
      "norm_pred": "sphlu hai jee koo kree citu laai",
      "ratio": 100.0,
      "token_sort_ratio": 100.0,
      "wratio": 100.0,
      "exact_norm": true
    },
    {
      "idx": 350,
      "audio": "training_data/silver_300h_holdout/clips/rChM6_mmWpQ_clip_00006.wav",
      "video_id": "rChM6_mmWpQ",
      "shabad_id": "R0K",
      "duration_s": 5.879,
      "label_score": 1.0,
      "target": "ਚਰਨ ਕਮਲ ਹਿਰਦੈ ਉਰਿ ਧਾਰੇ",
      "pred": "ਚਰਨ ਕਮਲ ਹਿਰਦੈ ਉਰਿ ਧਾਰੇ",
      "norm_target": "crn kml hirdai uri dhaaree",
      "norm_pred": "crn kml hirdai uri dhaaree",
      "ratio": 100.0,
      "token_sort_ratio": 100.0,
      "wratio": 100.0,
      "exact_norm": true
    },
    {
      "idx": 453,
      "audio": "training_data/silver_300h_holdout/clips/1zc7krygelw_clip_00004.wav",
      "video_id": "1zc7krygelw",
      "shabad_id": "JA8",
      "duration_s": 6.801,
      "label_score": 1.0,
      "target": "ਕੋ ਬਨਜਾਰੋ ਰਾਮ ਕੋ",
      "pred": "ਕੋ ਬਣਜਾਰੋ ਰਾਮ ਕੋ",
      "norm_target": "koo bnjaaroo raam koo",
      "norm_pred": "koo bnnjaaroo raam koo",
      "ratio": 97.67441860465115,
      "token_sort_ratio": 97.67441860465115,
      "wratio": 97.67441860465115,
      "exact_norm": false
    },
    {
      "idx": 531,
      "audio": "training_data/silver_300h_holdout/clips/2d_Wy2Vb6n4_clip_00002.wav",
      "video_id": "2d_Wy2Vb6n4",
      "shabad_id": "TA4",
      "duration_s": 7.231,
      "label_score": 1.0,
      "target": "ਥੀਆ ਸੰਤਨ ਬਿਨੁ ਅਵਰੁ ਨ ਦਾਤਾ",
      "pred": "ਪੀਆ ਸੰਤਨ ਬਿਨੁ ਅਵਰੁ ਨ ਦਾਤਾ",
      "norm_target": "thiiaa sntn binu avru n daataa",
      "norm_pred": "piiaa sntn binu avru n daataa",
      "ratio": 94.91525423728814,
      "token_sort_ratio": 77.96610169491525,
      "wratio": 94.91525423728814,
      "exact_norm": false
    },
    {
      "idx": 717,
      "audio": "training_data/silver_300h_holdout/clips/6xbaRKbOhPc_clip_00001.wav",
      "video_id": "6xbaRKbOhPc",
      "shabad_id": "J46",
      "duration_s": 8.125,
      "label_score": 1.0,
      "target": "ਹਮ ਰੁਲਤੇ ਫਿਰਤੇ ਕੋਈ ਬਾਤ ਨ ਪੂਛਤਾ",
      "pred": "ਹਮ ਰੁਲਤੇ ਫਿਰਤੇ ਕੋਈ ਬਾਤ ਨ ਪੂਛਤਾ",
      "norm_target": "hm rultee phirtee kooii baat n puuchtaa",
      "norm_pred": "hm rultee phirtee kooii baat n puuchtaa",
      "ratio": 100.0,
      "token_sort_ratio": 100.0,
      "wratio": 100.0,
      "exact_norm": true
    },
    {
      "idx": 890,
      "audio": "training_data/silver_300h_holdout/clips/9NWAGIUkfU4_clip_00005.wav",
      "video_id": "9NWAGIUkfU4",
      "shabad_id": "4G0",
      "duration_s": 18.979,
      "label_score": 1.0,
      "target": "ਸ੍ਰੀ ਗੁਰ ਰਾਮਦਾਸ",
      "pred": "ਸ੍ਰੀ ਗੁਰ ਰਾਮਦਾਸ",
      "norm_target": "srii gur raamdaas",
      "norm_pred": "srii gur raamdaas",
      "ratio": 100.0,
      "token_sort_ratio": 100.0,
      "wratio": 100.0,
      "exact_norm": true
    },
    {
      "idx": 1943,
      "audio": "training_data/silver_300h_holdout/clips/DNm47efW0po_clip_00003.wav",
      "video_id": "DNm47efW0po",
      "shabad_id": "1YU",
      "duration_s": 9.6,
      "label_score": 1.0,
      "target": "ਖੂਬੁ ਖੂਬੁ ਖੂਬੁ ਖੂਬੁ ਖੂਬੁ ਤੇਰੋ ਨਾਮੁ ਝੂਠੁ ਝੂਠੁ ਝੂਠੁ ਝੂਠੁ ਦੁਨੀ ਗੁਮਾਨੁ",
      "pred": "ਖੂਬੁ ਖੂਬੁ ਖੂਬੁ ਖੂਬੁ ਖੂਬੁ ਤੇਰੋ ਨਾਮੁ ਝੂਠੁ ਝੂਠੁ ਝੂਠੁ ਝੂਠੁ ਦੁਨੀ ਗੁਮਾਨੁ",
      "norm_target": "khuubu khuubu khuubu khuubu khuubu teeroo naamu jhuutthu jhuutthu jhuutthu jhuutthu dunii gumaanu",
      "norm_pred": "khuubu khuubu khuubu khuubu khuubu teeroo naamu jhuutthu jhuutthu jhuutthu jhuutthu dunii gumaanu",
      "ratio": 100.0,
      "token_sort_ratio": 100.0,
      "wratio": 100.0,
      "exact_norm": true
    },
    {
      "idx": 2882,
      "audio": "training_data/silver_300h_holdout/clips/HJ9h97PeRto_clip_00000.wav",
      "video_id": "HJ9h97PeRto",
      "shabad_id": "TDH",
      "duration_s": 7.2,
      "label_score": 1.0,
      "target": "ਮੈ ਬਿਨੁ ਗੁਰ ਦੇਖੇ ਨੀਦ ਨ ਆਵੈ",
      "pred": "ਮੈ ਬਿਨੁ ਗੁਰ ਦੇਖੇ ਨੀਦ ਨ ਆਵੈ",
      "norm_target": "mai binu gur deekhee niid n aavai",
      "norm_pred": "mai binu gur deekhee niid n aavai",
      "ratio": 100.0,
      "token_sort_ratio": 100.0,
      "wratio": 100.0,
      "exact_norm": true
    },
    {
      "idx": 3233,
      "audio": "training_data/silver_300h_holdout/clips/PYUPZn6wiR8_clip_00000.wav",
      "video_id": "PYUPZn6wiR8",
      "shabad_id": "VGA",
      "duration_s": 8.76,
      "label_score": 1.0,
      "target": "ਸੰਤ ਜਨਾ ਰਾਮ ਪਿਆਰੇ",
      "pred": "ਸਦਾ ਜਾਗੇ ਰਾਮ ਪਿਆਰੇ",
      "norm_target": "snt jnaa raam piaaree",
      "norm_pred": "sdaa jaagee raam piaaree",
      "ratio": 80.0,
      "token_sort_ratio": 80.0,
      "wratio": 80.0,
      "exact_norm": false
    },
    {
      "idx": 3288,
      "audio": "training_data/silver_300h_holdout/clips/SjkbOQTpBv0_clip_00000.wav",
      "video_id": "SjkbOQTpBv0",
      "shabad_id": "SC1",
      "duration_s": 6.2,
      "label_score": 1.0,
      "target": "ਮਿਹਰਵਾਨੁ ਸਾਹਿਬੁ ਮਿਹਰਵਾਨੁ",
      "pred": "ਮਿਹਰਵਾਨੁ ਸਾਹਿਬੁ ਮਿਹਰਵਾਨੁ",
      "norm_target": "mihrvaanu saahibu mihrvaanu",
      "norm_pred": "mihrvaanu saahibu mihrvaanu",
      "ratio": 100.0,
      "token_sort_ratio": 100.0,
      "wratio": 100.0,
      "exact_norm": true
    },
    {
      "idx": 3580,
      "audio": "training_data/silver_300h_holdout/clips/ZYmyfM8mkTw_clip_00003.wav",
      "video_id": "ZYmyfM8mkTw",
      "shabad_id": "JMP",
      "duration_s": 10.08,
      "label_score": 0.9230769230769231,
      "target": "ਤੂੰ ਜਲਿ ਥਲਿ ਮਹੀਅਲਿ ਭਰਿਪੁਰਿ ਲੀਣਾ ਤੂੰ ਆਪੇ ਸਰਬ ਸਮਾਣਾ ਮਨੁ ਤੁਲਾ ਜੀਓ",
      "pred": "ਤੂੰ ਜਲਿ ਥਲਿ ਮਹੀਅਲਿ ਭਰਿਪੁਰਿ ਲੀਣਾ ਤੂੰ ਆਪੇ ਸਰਬ ਸਮਾਣਾ ਮੇਰੇ ਲਾਲ ਜੀਉ",
      "norm_target": "tuun jli thli mhiiali bbripuri liinnaa tuun aapee srb smaannaa mnu tulaa jiioo",
      "norm_pred": "tuun jli thli mhiiali bbripuri liinnaa tuun aapee srb smaannaa meeree laal jiiu",
      "ratio": 91.71974522292994,
      "token_sort_ratio": 84.07643312101911,
      "wratio": 91.71974522292994,
      "exact_norm": false
    },
    {
      "idx": 4542,
      "audio": "training_data/silver_300h_holdout/clips/iQAbsSM5FO8_clip_00037.wav",
      "video_id": "iQAbsSM5FO8",
      "shabad_id": "F8K",
      "duration_s": 6.16,
      "label_score": 1.0,
      "target": "ਮਃ ਮਾਰੂ ਭੁਖ",
      "pred": "ਫਲ ਦੇ ਲਾਭੁ ਭੁਖ",
      "norm_target": "m maaruu bbukh",
      "norm_pred": "phl dee laabbu bbukh",
      "ratio": 58.82352941176471,
      "token_sort_ratio": 58.82352941176471,
      "wratio": 58.82352941176471,
      "exact_norm": false
    },
    {
      "idx": 4654,
      "audio": "training_data/silver_300h_holdout/clips/lV7e4k8K2q4_clip_00001.wav",
      "video_id": "lV7e4k8K2q4",
      "shabad_id": "5NM",
      "duration_s": 5.519,
      "label_score": 1.0,
      "target": "ਆਗੈ ਮਾਰਗਿ ਪਾਵੈ",
      "pred": "ਆਗੈ ਮਾਰਗਿ ਪਾਵੈ",
      "norm_target": "aagai maargi paavai",
      "norm_pred": "aagai maargi paavai",
      "ratio": 100.0,
      "token_sort_ratio": 100.0,
      "wratio": 100.0,
      "exact_norm": true
    },
    {
      "idx": 5711,
      "audio": "training_data/silver_300h_holdout/clips/pdMFF6A-4Fg_clip_00004.wav",
      "video_id": "pdMFF6A-4Fg",
      "shabad_id": "6X5",
      "duration_s": 3.96,
      "label_score": 1.0,
      "target": "ਨਦਰਿ ਕਰੇ",
      "pred": "ਨਦਰਿ ਕਰੇ",
      "norm_target": "ndri kree",
      "norm_pred": "ndri kree",
      "ratio": 100.0,
      "token_sort_ratio": 100.0,
      "wratio": 100.0,
      "exact_norm": true
    },
    {
      "idx": 6333,
      "audio": "training_data/silver_300h_holdout/clips/srf-mMyyozw_clip_00000.wav",
      "video_id": "srf-mMyyozw",
      "shabad_id": "A0N",
      "duration_s": 8.16,
      "label_score": 1.0,
      "target": "ਸੁਣੀ ਅਰਦਾਸਿ ਸੁਆਮੀ ਮੇਰੈ",
      "pred": "ਸੁਣੀ ਅਰਦਾਸਿ ਸੁਆਮੀ ਮੇਰੈ",
      "norm_target": "sunnii ardaasi suaamii meerai",
      "norm_pred": "sunnii ardaasi suaamii meerai",
      "ratio": 100.0,
      "token_sort_ratio": 100.0,
      "wratio": 100.0,
      "exact_norm": true
    },
    {
      "idx": 6672,
      "audio": "training_data/silver_300h_holdout/clips/zBX2woljpm8_clip_00004.wav",
      "video_id": "zBX2woljpm8",
      "shabad_id": "DPP",
      "duration_s": 7.641,
      "label_score": 1.0,
      "target": "ਬਿਨੁ ਨਾਮੈ ਧ੍ਰਿਗੁ ਜੀਵਾਸੁ",
      "pred": "ਬਿਨੁ ਨਾਮੈ ਧ੍ਰਿਗੁ ਜੀਵਾਸਾ",
      "norm_target": "binu naamai dhrigu jiivaasu",
      "norm_pred": "binu naamai dhrigu jiivaasaa",
      "ratio": 94.54545454545455,
      "token_sort_ratio": 94.54545454545455,
      "wratio": 94.54545454545455,
      "exact_norm": false
    },
    {
      "idx": 6787,
      "audio": "training_data/silver_300h_holdout/clips/0N7ZF7RRKtw_clip_00000.wav",
      "video_id": "0N7ZF7RRKtw",
      "shabad_id": "7DG",
      "duration_s": 2.56,
      "label_score": 1.0,
      "target": "ਵਾਹਿਗੁਰੂ ਵਾਹਿਗੁਰੂ",
      "pred": "ਵਾਹਿਗੁਰੂ ਵਾਹਿਗੁਰੂ",
      "norm_target": "vaahiguruu vaahiguruu",
      "norm_pred": "vaahiguruu vaahiguruu",
      "ratio": 100.0,
      "token_sort_ratio": 100.0,
      "wratio": 100.0,
      "exact_norm": true
    },
    {
      "idx": 6920,
      "audio": "training_data/silver_300h_holdout/clips/3H8WwqVcUL8_clip_00000.wav",
      "video_id": "3H8WwqVcUL8",
      "shabad_id": "UBH",
      "duration_s": 6.6,
      "label_score": 1.0,
      "target": "ਧਰਤਿ ਸੁਹਾਵੀ ਤਾਲੁ ਸੁਹਾਵਾ",
      "pred": "ਧਰਤਿ ਸੁਹਾਵੀ ਤਾਲੁ ਸੁਹਾਵਾ",
      "norm_target": "dhrti suhaavii taalu suhaavaa",
      "norm_pred": "dhrti suhaavii taalu suhaavaa",
      "ratio": 100.0,
      "token_sort_ratio": 100.0,
      "wratio": 100.0,
      "exact_norm": true
    },
    {
      "idx": 7606,
      "audio": "training_data/silver_300h_holdout/clips/7WkqVP6buv8_clip_00006.wav",
      "video_id": "7WkqVP6buv8",
      "shabad_id": "1U3",
      "duration_s": 5.72,
      "label_score": 1.0,
      "target": "ਬਿਘਨੁ ਨ ਕੋਊ ਲਾਗਤਾ",
      "pred": "ਬਿਘਨੁ ਨ ਕੋਊ ਲਾਗਤਾ",
      "norm_target": "bighnu n koouu laagtaa",
      "norm_pred": "bighnu n koouu laagtaa",
      "ratio": 100.0,
      "token_sort_ratio": 100.0,
      "wratio": 100.0,
      "exact_norm": true
    },
    {
      "idx": 1,
      "audio": "training_data/silver_300h_holdout/clips/njmuAa8IY80_clip_01679.wav",
      "video_id": "njmuAa8IY80",
      "shabad_id": "7TL",
      "duration_s": 6.96,
      "label_score": 1.0,
      "target": "ਸਤਿਗੁਰ ਕੀ ਸੇਵਾ ਸਫਲੁ ਹੈ",
      "pred": "ਸਤਿਗੁਰ ਕੀ ਸੇਵਾ ਸਫਲੁ ਹੈ",
      "norm_target": "stigur kii seevaa sphlu hai",
      "norm_pred": "stigur kii seevaa sphlu hai",
      "ratio": 100.0,
      "token_sort_ratio": 100.0,
      "wratio": 100.0,
      "exact_norm": true
    },
    {
      "idx": 351,
      "audio": "training_data/silver_300h_holdout/clips/rChM6_mmWpQ_clip_00010.wav",
      "video_id": "rChM6_mmWpQ",
      "shabad_id": "R0K",
      "duration_s": 6.841,
      "label_score": 1.0,
      "target": "ਤੇਰੇ ਦਰਸਨ ਕਉ ਜਾਈ ਬਲਿਹਾਰੇ",
      "pred": "ਤੇਰੇ ਦਰਸਨ ਕਉ ਬਲਿਹਾਰੇ",
      "norm_target": "teeree drsn ku jaaii blihaaree",
      "norm_pred": "teeree drsn ku blihaaree",
      "ratio": 88.88888888888889,
      "token_sort_ratio": 88.88888888888889,
      "wratio": 95.0,
      "exact_norm": false
    },
    {
      "idx": 454,
      "audio": "training_data/silver_300h_holdout/clips/1zc7krygelw_clip_00005.wav",
      "video_id": "1zc7krygelw",
      "shabad_id": "JA8",
      "duration_s": 4.8,
      "label_score": 1.0,
      "target": "ਮੇਰਾ ਟਾਂਡਾ ਲਾਦਿਆ",
      "pred": "ਮੇਰਾ ਟਾਂਡਾ ਲਾਦਿਆ",
      "norm_target": "meeraa ttaanddaa laadiaa",
      "norm_pred": "meeraa ttaanddaa laadiaa",
      "ratio": 100.0,
      "token_sort_ratio": 100.0,
      "wratio": 100.0,
      "exact_norm": true
    },
    {
      "idx": 532,
      "audio": "training_data/silver_300h_holdout/clips/2d_Wy2Vb6n4_clip_00003.wav",
      "video_id": "2d_Wy2Vb6n4",
      "shabad_id": "TA4",
      "duration_s": 7.329,
      "label_score": 1.0,
      "target": "ਥੀਆ ਸੰਤਨ ਬਿਨੁ ਅਵਰੁ ਨ ਦਾਤਾ",
      "pred": "ਥਾਪੀਆ ਸੰਤਨ ਬਿਨੁ ਅਵਰੁ ਨ ਦਾਤਾ",
      "norm_target": "thiiaa sntn binu avru n daataa",
      "norm_pred": "thaapiiaa sntn binu avru n daataa",
      "ratio": 95.23809523809523,
      "token_sort_ratio": 95.23809523809523,
      "wratio": 95.23809523809523,
      "exact_norm": false
    },
    {
      "idx": 718,
      "audio": "training_data/silver_300h_holdout/clips/6xbaRKbOhPc_clip_00002.wav",
      "video_id": "6xbaRKbOhPc",
      "shabad_id": "J46",
      "duration_s": 11.08,
      "label_score": 1.0,
      "target": "ਗੁਰ ਸਤਿਗੁਰ ਸੰਗਿ ਕੀਰੇ ਹਮ ਥਾਪੇ ਧੰਨੁ ਧੰਨੁ ਗੁਰੂ ਨਾਨਕ ਜਨ ਕੇਰਾ",
      "pred": "ਗੁਰ ਸਤਿਗੁਰ ਸੰਗਿ ਕੀਰੇ ਹਮ ਥਾਪੇ ਧੰਨ ਧੰਨ ਗੁਰੂ ਨਾਨਕ ਜਨ ਕੇ ਰਾਮ",
      "norm_target": "gur stigur sngi kiiree hm thaapee dhnnu dhnnu guruu naank jn keeraa",
      "norm_pred": "gur stigur sngi kiiree hm thaapee dhnn dhnn guruu naank jn kee raam",
      "ratio": 97.01492537313433,
      "token_sort_ratio": 92.53731343283582,
      "wratio": 97.01492537313433,
      "exact_norm": false
    },
    {
      "idx": 891,
      "audio": "training_data/silver_300h_holdout/clips/9NWAGIUkfU4_clip_00006.wav",
      "video_id": "9NWAGIUkfU4",
      "shabad_id": "4G0",
      "duration_s": 9.24,
      "label_score": 1.0,
      "target": "ਸਤਿਗੁਰਿ ਨਾਨਕਿ ਭਗਤਿ ਕਰੀ ਇਕ ਮਨਿ",
      "pred": "ਸਤਿਗੁਰਿ ਨਾਨਕਿ ਭਗਤਿ ਕਰੀ ਇਕ ਮਨਿ",
      "norm_target": "stiguri naanki bbgti krii ik mni",
      "norm_pred": "stiguri naanki bbgti krii ik mni",
      "ratio": 100.0,
      "token_sort_ratio": 100.0,
      "wratio": 100.0,
      "exact_norm": true
    },
    {
      "idx": 1944,
      "audio": "training_data/silver_300h_holdout/clips/DNm47efW0po_clip_00004.wav",
      "video_id": "DNm47efW0po",
      "shabad_id": "1YU",
      "duration_s": 8.68,
      "label_score": 0.9,
      "target": "ਖੂਬੁ ਖੂਬੁ ਖੂਬੁ ਖੂਬੁ ਖੂਬੁ ਤੇਰੋ ਨਾਮੁ ਝੂਠੁ ਝੂਠੁ झूठটਨੇ",
      "pred": "ਖੂਬੁ ਖੂਬੁ ਖੂਬੁ ਖੂਬੁ ਖੂਬੁ ਤੇਰੋ ਨਾਮੁ ਝੂਠੁ ਝੂਠੁ ਝੂਠੁ ਝੂਠੁ ਦੁਨੀ",
      "norm_target": "khuubu khuubu khuubu khuubu khuubu teeroo naamu jhuutthu jhuutthu jhuutthttnee",
      "norm_pred": "khuubu khuubu khuubu khuubu khuubu teeroo naamu jhuutthu jhuutthu jhuutthu jhuutthu dunii",
      "ratio": 91.01796407185628,
      "token_sort_ratio": 89.82035928143712,
      "wratio": 91.01796407185628,
      "exact_norm": false
    },
    {
      "idx": 2883,
      "audio": "training_data/silver_300h_holdout/clips/HJ9h97PeRto_clip_00001.wav",
      "video_id": "HJ9h97PeRto",
      "shabad_id": "TDH",
      "duration_s": 6.8,
      "label_score": 1.0,
      "target": "ਮੈ ਬਿਨੁ ਗੁਰ ਦੇਖੇ ਨੀਦ ਨ ਆਵੈ",
      "pred": "ਮੈ ਬਿਨੁ ਗੁਰ ਦੇਖੇ ਨੀਦ ਨ ਆਵੈ",
      "norm_target": "mai binu gur deekhee niid n aavai",
      "norm_pred": "mai binu gur deekhee niid n aavai",
      "ratio": 100.0,
      "token_sort_ratio": 100.0,
      "wratio": 100.0,
      "exact_norm": true
    },
    {
      "idx": 3234,
      "audio": "training_data/silver_300h_holdout/clips/PYUPZn6wiR8_clip_00001.wav",
      "video_id": "PYUPZn6wiR8",
      "shabad_id": "VGA",
      "duration_s": 8.521,
      "label_score": 1.0,
      "target": "ਸੰਤ ਜਨਾ ਰਾਮ ਪਿਆਰੇ",
      "pred": "ਸਦਾ ਕੇ ਰਾਮ ਪਿਆਰੇ",
      "norm_target": "snt jnaa raam piaaree",
      "norm_pred": "sdaa kee raam piaaree",
      "ratio": 76.19047619047619,
      "token_sort_ratio": 71.42857142857143,
      "wratio": 76.19047619047619,
      "exact_norm": false
    },
    {
      "idx": 3289,
      "audio": "training_data/silver_300h_holdout/clips/SjkbOQTpBv0_clip_00001.wav",
      "video_id": "SjkbOQTpBv0",
      "shabad_id": "SC1",
      "duration_s": 5.4,
      "label_score": 1.0,
      "target": "ਸਾਹਿਬੁ ਮੇਰਾ ਮਿਹਰਵਾਨੁ",
      "pred": "ਸਾਹਿਬੁ ਮੇਰਾ ਮਿਹਰਵਾਨੁ",
      "norm_target": "saahibu meeraa mihrvaanu",
      "norm_pred": "saahibu meeraa mihrvaanu",
      "ratio": 100.0,
      "token_sort_ratio": 100.0,
      "wratio": 100.0,
      "exact_norm": true
    },
    {
      "idx": 3581,
      "audio": "training_data/silver_300h_holdout/clips/ZYmyfM8mkTw_clip_00005.wav",
      "video_id": "ZYmyfM8mkTw",
      "shabad_id": "JMP",
      "duration_s": 7.16,
      "label_score": 1.0,
      "target": "ਕਉਣ ਤਰਾਜੀ ਕਵਣੁ ਤੁਲਾ",
      "pred": "ਕਉਣ ਤਰਾਜੀ ਕਵਣੁ ਤੁਲਾ",
      "norm_target": "kunn traajii kvnnu tulaa",
      "norm_pred": "kunn traajii kvnnu tulaa",
      "ratio": 100.0,
      "token_sort_ratio": 100.0,
      "wratio": 100.0,
      "exact_norm": true
    },
    {
      "idx": 4543,
      "audio": "training_data/silver_300h_holdout/clips/iQAbsSM5FO8_clip_00048.wav",
      "video_id": "iQAbsSM5FO8",
      "shabad_id": "8ES",
      "duration_s": 5.68,
      "label_score": 1.0,
      "target": "ਆਪੇ ਸਿਰਿ ਲੇਖੈ",
      "pred": "ਆਪਿ ਸਖਲੇ ਦੁਖ",
      "norm_target": "aapee siri leekhai",
      "norm_pred": "aapi skhlee dukh",
      "ratio": 58.82352941176471,
      "token_sort_ratio": 47.05882352941176,
      "wratio": 58.82352941176471,
      "exact_norm": false
    },
    {
      "idx": 4655,
      "audio": "training_data/silver_300h_holdout/clips/lV7e4k8K2q4_clip_00002.wav",
      "video_id": "lV7e4k8K2q4",
      "shabad_id": "5NM",
      "duration_s": 7.681,
      "label_score": 1.0,
      "target": "ਪਿਛਲੇ ਅਉਗੁਣ ਬਖਸਿ ਲਏ ਪ੍ਰਭੁ",
      "pred": "ਪਿਛਲੇ ਅਗਣ ਬਖਸਿ ਲਏ ਪ੍ਰਭੁ",
      "norm_target": "pichlee augunn bkhsi lee prbbu",
      "norm_pred": "pichlee agnn bkhsi lee prbbu",
      "ratio": 96.55172413793103,
      "token_sort_ratio": 96.55172413793103,
      "wratio": 96.55172413793103,
      "exact_norm": false
    },
    {
      "idx": 5712,
      "audio": "training_data/silver_300h_holdout/clips/pdMFF6A-4Fg_clip_00009.wav",
      "video_id": "pdMFF6A-4Fg",
      "shabad_id": "HYC",
      "duration_s": 7.28,
      "label_score": 1.0,
      "target": "ਸਭੇ ਥੋਕ ਪਰਾਪਤੇ ਜੇ ਆਵੈ ਇਕੁ ਹਥਿ",
      "pred": "ਸਭੇ ਥੋਕ ਪਰਾਪਤੇ ਜੇ ਆਵੈ ਇਕੁ ਹਥਿ",
      "norm_target": "sbbee thook praaptee jee aavai iku hthi",
      "norm_pred": "sbbee thook praaptee jee aavai iku hthi",
      "ratio": 100.0,
      "token_sort_ratio": 100.0,
      "wratio": 100.0,
      "exact_norm": true
    },
    {
      "idx": 6334,
      "audio": "training_data/silver_300h_holdout/clips/srf-mMyyozw_clip_00002.wav",
      "video_id": "srf-mMyyozw",
      "shabad_id": "A0N",
      "duration_s": 9.32,
      "label_score": 1.0,
      "target": "ਸੁਆਮੀ ਮੇਰੈ ਸਰਬ ਕਲਾ ਬਣਿ ਆਈ",
      "pred": "ਸੁਆਮੀ ਮੇਰੈ ਸਰਬ ਕਲਾ ਬਣਿ ਆਈ",
      "norm_target": "suaamii meerai srb klaa bnni aaii",
      "norm_pred": "suaamii meerai srb klaa bnni aaii",
      "ratio": 100.0,
      "token_sort_ratio": 100.0,
      "wratio": 100.0,
      "exact_norm": true
    },
    {
      "idx": 6673,
      "audio": "training_data/silver_300h_holdout/clips/zBX2woljpm8_clip_00005.wav",
      "video_id": "zBX2woljpm8",
      "shabad_id": "DPP",
      "duration_s": 6.04,
      "label_score": 1.0,
      "target": "ਕੋਈ ਗੁਰਮੁਖਿ ਸਜਣੁ ਜੇ ਮਿਲੈ",
      "pred": "ਕੋਈ ਗੁਰਮੁਖਿ ਸਜਣੁ ਜੇ ਮਿਲੈ",
      "norm_target": "kooii gurmukhi sjnnu jee milai",
      "norm_pred": "kooii gurmukhi sjnnu jee milai",
      "ratio": 100.0,
      "token_sort_ratio": 100.0,
      "wratio": 100.0,
      "exact_norm": true
    },
    {
      "idx": 6788,
      "audio": "training_data/silver_300h_holdout/clips/0N7ZF7RRKtw_clip_00001.wav",
      "video_id": "0N7ZF7RRKtw",
      "shabad_id": "7DG",
      "duration_s": 4.68,
      "label_score": 1.0,
      "target": "ਵਾਹਿਗੁਰੂ ਵਾਹਿਗੁਰੂ",
      "pred": "ਵਾਹਿਗੁਰੂ ਵਾਹਿਗੁਰੂ",
      "norm_target": "vaahiguruu vaahiguruu",
      "norm_pred": "vaahiguruu vaahiguruu",
      "ratio": 100.0,
      "token_sort_ratio": 100.0,
      "wratio": 100.0,
      "exact_norm": true
    },
    {
      "idx": 6921,
      "audio": "training_data/silver_300h_holdout/clips/3H8WwqVcUL8_clip_00001.wav",
      "video_id": "3H8WwqVcUL8",
      "shabad_id": "UBH",
      "duration_s": 5.2,
      "label_score": 1.0,
      "target": "ਧਰਤਿ ਸੁਹਾਵੀ ਤਾਲੁ ਸੁਹਾਵਾ",
      "pred": "ਧਰਤਿ ਸੁਹਾਵੀ ਤਾਲੁ ਸੁਹਾਵਾ",
      "norm_target": "dhrti suhaavii taalu suhaavaa",
      "norm_pred": "dhrti suhaavii taalu suhaavaa",
      "ratio": 100.0,
      "token_sort_ratio": 100.0,
      "wratio": 100.0,
      "exact_norm": true
    },
    {
      "idx": 7607,
      "audio": "training_data/silver_300h_holdout/clips/7WkqVP6buv8_clip_00007.wav",
      "video_id": "7WkqVP6buv8",
      "shabad_id": "1U3",
      "duration_s": 5.719,
      "label_score": 1.0,
      "target": "ਬਿਘਨੁ ਨ ਕੋਊ ਲਾਗਤਾ",
      "pred": "ਬਿਘਨੁ ਨ ਕੋਊ ਲਾਗਤਾ",
      "norm_target": "bighnu n koouu laagtaa",
      "norm_pred": "bighnu n koouu laagtaa",
      "ratio": 100.0,
      "token_sort_ratio": 100.0,
      "wratio": 100.0,
      "exact_norm": true
    },
    {
      "idx": 2,
      "audio": "training_data/silver_300h_holdout/clips/njmuAa8IY80_clip_01680.wav",
      "video_id": "njmuAa8IY80",
      "shabad_id": "BP7",
      "duration_s": 7.199,
      "label_score": 1.0,
      "target": "ਜੇ ਕੋ ਕਰੇ ਚਿਤੁ ਲਾਇ ਜੇ ਕੋ ਕਰੇ",
      "pred": "ਜੇ ਕੋ ਕਰੇ ਚਿਤੁ ਲਾਇ ਜੇ ਕੋ ਕਰੇ",
      "norm_target": "jee koo kree citu laai jee koo kree",
      "norm_pred": "jee koo kree citu laai jee koo kree",
      "ratio": 100.0,
      "token_sort_ratio": 100.0,
      "wratio": 100.0,
      "exact_norm": true
    },
    {
      "idx": 352,
      "audio": "training_data/silver_300h_holdout/clips/rChM6_mmWpQ_clip_00011.wav",
      "video_id": "rChM6_mmWpQ",
      "shabad_id": "R0K",
      "duration_s": 10.56,
      "label_score": 1.0,
      "target": "ਤੇਰੇ ਦਰਸਨ ਕਉ ਜਾਈ ਬਲਿਹਾਰੇ ਚਰਨ ਕਮਲ ਹਿਰਦੈ ਉਰਿ ਧਾਰੇ",
      "pred": "ਤੇਰੇ ਦਰਸਨ ਕਉ ਜਾਈ ਬਲਿਹਾਰੇ ਚਰਨ ਕਮਲ ਹਿਰਦੈ ਉਰਿ ਧਾਰੇ",
      "norm_target": "teeree drsn ku jaaii blihaaree crn kml hirdai uri dhaaree",
      "norm_pred": "teeree drsn ku jaaii blihaaree crn kml hirdai uri dhaaree",
      "ratio": 100.0,
      "token_sort_ratio": 100.0,
      "wratio": 100.0,
      "exact_norm": true
    },
    {
      "idx": 455,
      "audio": "training_data/silver_300h_holdout/clips/1zc7krygelw_clip_00007.wav",
      "video_id": "1zc7krygelw",
      "shabad_id": "JA8",
      "duration_s": 5.199,
      "label_score": 1.0,
      "target": "ਰਾਮ ਕੋ ਮੇਰਾ",
      "pred": "ਰਾਮ ਕੋ ਮੇਰਾ",
      "norm_target": "raam koo meeraa",
      "norm_pred": "raam koo meeraa",
      "ratio": 100.0,
      "token_sort_ratio": 100.0,
      "wratio": 100.0,
      "exact_norm": true
    },
    {
      "idx": 533,
      "audio": "training_data/silver_300h_holdout/clips/2d_Wy2Vb6n4_clip_00004.wav",
      "video_id": "2d_Wy2Vb6n4",
      "shabad_id": "TA4",
      "duration_s": 6.881,
      "label_score": 1.0,
      "target": "ਥੀਆ ਸੰਤਨ ਬਿਨੁ ਅਵਰੁ ਨ ਦਾਤਾ",
      "pred": "ਥੀਆ ਸੰਤਨ ਬਿਨੁ ਅਵਰੁ ਨ ਦਾਤਾ",
      "norm_target": "thiiaa sntn binu avru n daataa",
      "norm_pred": "thiiaa sntn binu avru n daataa",
      "ratio": 100.0,
      "token_sort_ratio": 100.0,
      "wratio": 100.0,
      "exact_norm": true
    },
    {
      "idx": 719,
      "audio": "training_data/silver_300h_holdout/clips/6xbaRKbOhPc_clip_00003.wav",
      "video_id": "6xbaRKbOhPc",
      "shabad_id": "J46",
      "duration_s": 11.601,
      "label_score": 0.9166666666666666,
      "target": "ਜਿਤੁ ਮਿਲਿਐ ਚੂਕੇ ਸਭਿ ਸੰਗਿ ਸੰਤਾਪੇ ਧੰਨੁ ਧੰਨੁ ਗੁਰੂ ਨਾਨਕ ਜਨ ਕੇਰਾ",
      "pred": "ਜਿਤੁ ਮਿਲਿਐ ਚੂਕੇ ਸਭਿ ਸੋਗ ਸੰਤਾਪੇ ਧੰਨੁ ਧੰਨੁ ਗੁਰੂ ਨਾਨਕ ਜਨ ਕੇਰਾ",
      "norm_target": "jitu miliai cuukee sbbi sngi sntaapee dhnnu dhnnu guruu naank jn keeraa",
      "norm_pred": "jitu miliai cuukee sbbi soog sntaapee dhnnu dhnnu guruu naank jn keeraa",
      "ratio": 97.1830985915493,
      "token_sort_ratio": 92.95774647887323,
      "wratio": 97.1830985915493,
      "exact_norm": false
    },
    {
      "idx": 892,
      "audio": "training_data/silver_300h_holdout/clips/9NWAGIUkfU4_clip_00011.wav",
      "video_id": "9NWAGIUkfU4",
      "shabad_id": "4G0",
      "duration_s": 3.799,
      "label_score": 1.0,
      "target": "ਮੂਰਤਿ ਨਿਜ ਧਾਰੀ",
      "pred": "ਮੂਰਤਿ ਨਿਜ ਧਾਰੀ",
      "norm_target": "muurti nij dhaarii",
      "norm_pred": "muurti nij dhaarii",
      "ratio": 100.0,
      "token_sort_ratio": 100.0,
      "wratio": 100.0,
      "exact_norm": true
    },
    {
      "idx": 1945,
      "audio": "training_data/silver_300h_holdout/clips/DNm47efW0po_clip_00016.wav",
      "video_id": "DNm47efW0po",
      "shabad_id": "1YU",
      "duration_s": 9.76,
      "label_score": 1.0,
      "target": "ਨਗਜ ਤੇਰੇ ਬੰਦੇ ਦੀਦਾਰੁ ਅਪਾਰੁ ਨਾਮ ਬਿਨਾ ਸਭ ਦੁਨੀਆ ਛਾਰੁ",
      "pred": "ਨਗਜ ਤੇਰੇ ਬੰਦੇ ਦੀਦਾਰੁ ਅਪਾਰੁ ਨਾਮ ਬਿਨਾ ਸਭ ਦੁਨੀਆ ਛਾਰੁ",
      "norm_target": "ngj teeree bndee diidaaru apaaru naam binaa sbb duniiaa chaaru",
      "norm_pred": "ngj teeree bndee diidaaru apaaru naam binaa sbb duniiaa chaaru",
      "ratio": 100.0,
      "token_sort_ratio": 100.0,
      "wratio": 100.0,
      "exact_norm": true
    },
    {
      "idx": 2884,
      "audio": "training_data/silver_300h_holdout/clips/HJ9h97PeRto_clip_00002.wav",
      "video_id": "HJ9h97PeRto",
      "shabad_id": "TDH",
      "duration_s": 6.719,
      "label_score": 1.0,
      "target": "ਮੈ ਬਿਨੁ ਗੁਰ ਦੇਖੇ ਨੀਦ ਨ ਆਵੈ",
      "pred": "ਮੈ ਬਿਨੁ ਗੁਰ ਦੇਖੇ ਨੀਦ ਨ ਆਵੈ",
      "norm_target": "mai binu gur deekhee niid n aavai",
      "norm_pred": "mai binu gur deekhee niid n aavai",
      "ratio": 100.0,
      "token_sort_ratio": 100.0,
      "wratio": 100.0,
      "exact_norm": true
    },
    {
      "idx": 3235,
      "audio": "training_data/silver_300h_holdout/clips/PYUPZn6wiR8_clip_00002.wav",
      "video_id": "PYUPZn6wiR8",
      "shabad_id": "VGA",
      "duration_s": 8.6,
      "label_score": 1.0,
      "target": "ਸੰਤ ਜਨਾ ਰਾਮ ਪਿਆਰੇ",
      "pred": "ਸਦਾ ਜਾਗੇ ਰਾਮ ਪਿਆਰੇ",
      "norm_target": "snt jnaa raam piaaree",
      "norm_pred": "sdaa jaagee raam piaaree",
      "ratio": 80.0,
      "token_sort_ratio": 80.0,
      "wratio": 80.0,
      "exact_norm": false
    },
    {
      "idx": 3290,
      "audio": "training_data/silver_300h_holdout/clips/SjkbOQTpBv0_clip_00002.wav",
      "video_id": "SjkbOQTpBv0",
      "shabad_id": "SC1",
      "duration_s": 6.2,
      "label_score": 1.0,
      "target": "ਮਿਹਰਵਾਨੁ ਸਾਹਿਬੁ ਮਿਹਰਵਾਨੁ",
      "pred": "ਮਿਹਰਵਾਨੁ ਸਾਹਿਬੁ ਮਿਹਰਵਾਨੁ",
      "norm_target": "mihrvaanu saahibu mihrvaanu",
      "norm_pred": "mihrvaanu saahibu mihrvaanu",
      "ratio": 100.0,
      "token_sort_ratio": 100.0,
      "wratio": 100.0,
      "exact_norm": true
    },
    {
      "idx": 3582,
      "audio": "training_data/silver_300h_holdout/clips/ZYmyfM8mkTw_clip_00006.wav",
      "video_id": "ZYmyfM8mkTw",
      "shabad_id": "JMP",
      "duration_s": 6.399,
      "label_score": 1.0,
      "target": "ਕਉਣ ਤਰਾਜੀ ਕਵਣੁ ਤੁਲਾ",
      "pred": "ਕਉਣ ਤਰਾਜੀ ਕਵਣੁ ਤੁਲਾ",
      "norm_target": "kunn traajii kvnnu tulaa",
      "norm_pred": "kunn traajii kvnnu tulaa",
      "ratio": 100.0,
      "token_sort_ratio": 100.0,
      "wratio": 100.0,
      "exact_norm": true
    },
    {
      "idx": 4544,
      "audio": "training_data/silver_300h_holdout/clips/iQAbsSM5FO8_clip_00055.wav",
      "video_id": "iQAbsSM5FO8",
      "shabad_id": "MVN",
      "duration_s": 3.96,
      "label_score": 1.0,
      "target": "ਧਨਿ ਰੁਚ ਇਆ",
      "pred": "ਮਨਿ ਪਰਚਾਇਆ",
      "norm_target": "dhni ruc iaa",
      "norm_pred": "mni prcaaiaa",
      "ratio": 66.66666666666667,
      "token_sort_ratio": 50.0,
      "wratio": 66.66666666666667,
      "exact_norm": false
    },
    {
      "idx": 4656,
      "audio": "training_data/silver_300h_holdout/clips/lV7e4k8K2q4_clip_00003.wav",
      "video_id": "lV7e4k8K2q4",
      "shabad_id": "5NM",
      "duration_s": 5.599,
      "label_score": 1.0,
      "target": "ਆਗੈ ਮਾਰਗਿ ਪਾਵੈ",
      "pred": "ਆਗੈ ਮਾਰਗਿ ਪਾਵੈ",
      "norm_target": "aagai maargi paavai",
      "norm_pred": "aagai maargi paavai",
      "ratio": 100.0,
      "token_sort_ratio": 100.0,
      "wratio": 100.0,
      "exact_norm": true
    },
    {
      "idx": 5713,
      "audio": "training_data/silver_300h_holdout/clips/pdMFF6A-4Fg_clip_00010.wav",
      "video_id": "pdMFF6A-4Fg",
      "shabad_id": "HYC",
      "duration_s": 6.475,
      "label_score": 1.0,
      "target": "ਜਨਮੁ ਪਦਾਰਥੁ ਸਫਲੁ ਹੈ ਜੇ ਸਚਾ ਸਬਦੁ",
      "pred": "ਜਨਮੁ ਪਦਾਰਥੁ ਸਫਲੁ ਹੈ ਜੇ ਸਚਾ ਸਬਦੁ",
      "norm_target": "jnmu pdaarthu sphlu hai jee scaa sbdu",
      "norm_pred": "jnmu pdaarthu sphlu hai jee scaa sbdu",
      "ratio": 100.0,
      "token_sort_ratio": 100.0,
      "wratio": 100.0,
      "exact_norm": true
    },
    {
      "idx": 6335,
      "audio": "training_data/silver_300h_holdout/clips/srf-mMyyozw_clip_00003.wav",
      "video_id": "srf-mMyyozw",
      "shabad_id": "A0N",
      "duration_s": 3.441,
      "label_score": 1.0,
      "target": "ਸੁਣੀ ਅਰਦਾਸਿ",
      "pred": "ਸੁਣੀ ਅਰਦਾਸਿ",
      "norm_target": "sunnii ardaasi",
      "norm_pred": "sunnii ardaasi",
      "ratio": 100.0,
      "token_sort_ratio": 100.0,
      "wratio": 100.0,
      "exact_norm": true
    },
    {
      "idx": 6674,
      "audio": "training_data/silver_300h_holdout/clips/zBX2woljpm8_clip_00006.wav",
      "video_id": "zBX2woljpm8",
      "shabad_id": "DPP",
      "duration_s": 7.88,
      "label_score": 1.0,
      "target": "ਕੋਈ ਗੁਰਮੁਖਿ ਸਜਣੁ",
      "pred": "ਕੋਈ ਗੁਰਮੁਖਿ ਸਜਣੁ",
      "norm_target": "kooii gurmukhi sjnnu",
      "norm_pred": "kooii gurmukhi sjnnu",
      "ratio": 100.0,
      "token_sort_ratio": 100.0,
      "wratio": 100.0,
      "exact_norm": true
    },
    {
      "idx": 6789,
      "audio": "training_data/silver_300h_holdout/clips/0N7ZF7RRKtw_clip_00002.wav",
      "video_id": "0N7ZF7RRKtw",
      "shabad_id": "W2D",
      "duration_s": 9.961,
      "label_score": 1.0,
      "target": "ਯਾਰ ਵੇ ਨਿਤ ਸੁਖ ਸੁਖੇਦੀ ਸਾ ਮੈ ਪਾਈ",
      "pred": "ਯਾਰ ਨਿਤ ਸੁਖ ਸੁਖੇਦੀ ਸਾ ਮੈ ਪਾਈ",
      "norm_target": "yaar vee nit sukh sukheedii saa mai paaii",
      "norm_pred": "yaar nit sukh sukheedii saa mai paaii",
      "ratio": 94.87179487179486,
      "token_sort_ratio": 94.87179487179486,
      "wratio": 95.0,
      "exact_norm": false
    },
    {
      "idx": 6922,
      "audio": "training_data/silver_300h_holdout/clips/3H8WwqVcUL8_clip_00002.wav",
      "video_id": "3H8WwqVcUL8",
      "shabad_id": "UBH",
      "duration_s": 8.719,
      "label_score": 1.0,
      "target": "ਵਿਚਿ ਅੰਮ੍ਰਿਤ ਜਲੁ ਛਾਇਆ ਰਾਮ ਹਰਿ ਕੰਮੁ ਕਰਾਵਣਿ",
      "pred": "ਵਿਚਿ ਅੰਮ੍ਰਿਤ ਜਲੁ ਛਾਇਆ ਰਾਮ ਹਰਿ ਕੰਮੁ ਕਰਾਵਣਿ",
      "norm_target": "vici anmrit jlu chaaiaa raam hri knmu kraavnni",
      "norm_pred": "vici anmrit jlu chaaiaa raam hri knmu kraavnni",
      "ratio": 100.0,
      "token_sort_ratio": 100.0,
      "wratio": 100.0,
      "exact_norm": true
    },
    {
      "idx": 7608,
      "audio": "training_data/silver_300h_holdout/clips/7WkqVP6buv8_clip_00011.wav",
      "video_id": "7WkqVP6buv8",
      "shabad_id": "1U3",
      "duration_s": 8.72,
      "label_score": 1.0,
      "target": "ਭਗਤਨ ਕੀ ਰਾਸਿ ਰਖਵਾਲਾ ਗੋਬਿੰਦ ਰਾਇ",
      "pred": "ਭਗਤਨ ਕੀ ਰਾਸਿ ਰਖਵਾਲਾ ਗੋਬਿੰਦ ਰਾਇ",
      "norm_target": "bbgtn kii raasi rkhvaalaa goobind raai",
      "norm_pred": "bbgtn kii raasi rkhvaalaa goobind raai",
      "ratio": 100.0,
      "token_sort_ratio": 100.0,
      "wratio": 100.0,
      "exact_norm": true
    },
    {
      "idx": 3,
      "audio": "training_data/silver_300h_holdout/clips/njmuAa8IY80_clip_01682.wav",
      "video_id": "njmuAa8IY80",
      "shabad_id": "7TL",
      "duration_s": 6.994,
      "label_score": 1.0,
      "target": "ਸਤਿਗੁਰ ਕੀ ਸੇਵਾ ਸਫਲੁ ਹੈ",
      "pred": "ਸਤਿਗੁਰ ਕੀ ਸੇਵਾ ਸਫਲੁ ਹੈ",
      "norm_target": "stigur kii seevaa sphlu hai",
      "norm_pred": "stigur kii seevaa sphlu hai",
      "ratio": 100.0,
      "token_sort_ratio": 100.0,
      "wratio": 100.0,
      "exact_norm": true
    },
    {
      "idx": 353,
      "audio": "training_data/silver_300h_holdout/clips/rChM6_mmWpQ_clip_00014.wav",
      "video_id": "rChM6_mmWpQ",
      "shabad_id": "R0K",
      "duration_s": 7.961,
      "label_score": 1.0,
      "target": "ਸੁਣਿ ਸੁਣਿ ਜੀਵਾ ਨਾਮੁ ਤੁਮਾਰਾ",
      "pred": "ਸੁਣਿ ਸੁਣਿ ਜੀਵਾ ਨਾਮੁ ਤੁਮਾਰਾ",
      "norm_target": "sunni sunni jiivaa naamu tumaaraa",
      "norm_pred": "sunni sunni jiivaa naamu tumaaraa",
      "ratio": 100.0,
      "token_sort_ratio": 100.0,
      "wratio": 100.0,
      "exact_norm": true
    },
    {
      "idx": 456,
      "audio": "training_data/silver_300h_holdout/clips/1zc7krygelw_clip_00008.wav",
      "video_id": "1zc7krygelw",
      "shabad_id": "JA8",
      "duration_s": 6.841,
      "label_score": 1.0,
      "target": "ਟਾਂਡਾ ਲਾਦਿਆ ਜਾਇ ਰੇ",
      "pred": "ਟਾਂਡਾ ਲਾਦਿਆ ਜਾਇ ਰੇ",
      "norm_target": "ttaanddaa laadiaa jaai ree",
      "norm_pred": "ttaanddaa laadiaa jaai ree",
      "ratio": 100.0,
      "token_sort_ratio": 100.0,
      "wratio": 100.0,
      "exact_norm": true
    },
    {
      "idx": 534,
      "audio": "training_data/silver_300h_holdout/clips/2d_Wy2Vb6n4_clip_00005.wav",
      "video_id": "2d_Wy2Vb6n4",
      "shabad_id": "TA4",
      "duration_s": 6.96,
      "label_score": 1.0,
      "target": "ਥੀਆ ਸੰਤਨ ਬਿਨੁ ਅਵਰੁ ਨ ਦਾਤਾ",
      "pred": "ਥੀਆ ਸੰਤਨ ਬਿਨੁ ਅਵਰੁ ਨ ਦਾਤਾ",
      "norm_target": "thiiaa sntn binu avru n daataa",
      "norm_pred": "thiiaa sntn binu avru n daataa",
      "ratio": 100.0,
      "token_sort_ratio": 100.0,
      "wratio": 100.0,
      "exact_norm": true
    },
    {
      "idx": 720,
      "audio": "training_data/silver_300h_holdout/clips/6xbaRKbOhPc_clip_00006.wav",
      "video_id": "6xbaRKbOhPc",
      "shabad_id": "5SV",
      "duration_s": 10.479,
      "label_score": 1.0,
      "target": "ਭਗਤਾ ਕੀ ਟੇਕ ਤੂੰ ਸੰਤਾ ਕੀ ਓਟ ਤੂੰ",
      "pred": "ਭਗਤਾ ਕੀ ਟੇਕ ਤੂੰ ਸੰਤਾ ਕੀ ਓਟ ਤੂੰ",
      "norm_target": "bbgtaa kii tteek tuun sntaa kii oott tuun",
      "norm_pred": "bbgtaa kii tteek tuun sntaa kii oott tuun",
      "ratio": 100.0,
      "token_sort_ratio": 100.0,
      "wratio": 100.0,
      "exact_norm": true
    },
    {
      "idx": 893,
      "audio": "training_data/silver_300h_holdout/clips/9NWAGIUkfU4_clip_00023.wav",
      "video_id": "9NWAGIUkfU4",
      "shabad_id": "5BD",
      "duration_s": 15.32,
      "label_score": 0.9375,
      "target": "ਅਗਮੁ ਅਨੰਤੁ ਅਨਾਦਿ ਆਦਿ ਜਿਸੁ ਕੋਇ ਨ ਜਾਣੈ ਸਿਵ ਬਿਰੰਚਿ ਧਰਿ ਧਿਆਨ ਨਿਤਹਿ ਜਿਸੁ ਬੇਦੁ ਬਖਾਣੈ",
      "pred": "ਅਗਮੁ ਅਨੰਤੁ ਅਨਾਦਿ ਆਦਿ ਜਿਸੁ ਕੋਇ ਨ ਜਾਣੈ ਸਿਵ ਬਿਰੰਚਿ ਧਰਿ ਧਿਆਨ ਨਿਤਹਿ ਜਿਸੁ ਬੇਦੁ ਬਖਾਣੈ",
      "norm_target": "agmu anntu anaadi aadi jisu kooi n jaannai siv birnci dhri dhiaan nithi jisu beedu bkhaannai",
      "norm_pred": "agmu anntu anaadi aadi jisu kooi n jaannai siv birnci dhri dhiaan nithi jisu beedu bkhaannai",
      "ratio": 100.0,
      "token_sort_ratio": 100.0,
      "wratio": 100.0,
      "exact_norm": true
    },
    {
      "idx": 1946,
      "audio": "training_data/silver_300h_holdout/clips/DNm47efW0po_clip_00022.wav",
      "video_id": "DNm47efW0po",
      "shabad_id": "1YU",
      "duration_s": 9.76,
      "label_score": 1.0,
      "target": "ਨਗਜ ਤੇਰੇ ਬੰਦੇ ਦੀਦਾਰੁ ਅਪਾਰੁ ਨਾਮ ਬਿਨਾ ਸਭ ਦੁਨੀਆ ਛਾਰੁ",
      "pred": "ਨਗਜ ਤੇਰੇ ਬੰਦੇ ਦੀਦਾਰੁ ਅਪਾਰੁ ਨਾਮ ਬਿਨਾ ਸਭ ਦੁਨੀਆ ਛਾਰੁ",
      "norm_target": "ngj teeree bndee diidaaru apaaru naam binaa sbb duniiaa chaaru",
      "norm_pred": "ngj teeree bndee diidaaru apaaru naam binaa sbb duniiaa chaaru",
      "ratio": 100.0,
      "token_sort_ratio": 100.0,
      "wratio": 100.0,
      "exact_norm": true
    },
    {
      "idx": 2885,
      "audio": "training_data/silver_300h_holdout/clips/HJ9h97PeRto_clip_00003.wav",
      "video_id": "HJ9h97PeRto",
      "shabad_id": "TDH",
      "duration_s": 6.801,
      "label_score": 1.0,
      "target": "ਮੇਰੇ ਮਨ ਤਨਿ ਵੇਦਨ ਗੁਰ ਬਿਰਹੁ ਲਗਾਵੈ",
      "pred": "ਮੇਰੇ ਮਨ ਤਨਿ ਵੇਦਨ ਗੁਰ ਬਿਰਹੁ ਲਗਾਵੈ",
      "norm_target": "meeree mn tni veedn gur birhu lgaavai",
      "norm_pred": "meeree mn tni veedn gur birhu lgaavai",
      "ratio": 100.0,
      "token_sort_ratio": 100.0,
      "wratio": 100.0,
      "exact_norm": true
    },
    {
      "idx": 3236,
      "audio": "training_data/silver_300h_holdout/clips/PYUPZn6wiR8_clip_00019.wav",
      "video_id": "PYUPZn6wiR8",
      "shabad_id": "VGA",
      "duration_s": 7.8,
      "label_score": 1.0,
      "target": "ਸੰਤ ਜਨਾ ਰਾਮ ਪਿਆਰੇ",
      "pred": "ਸਦਾ ਜਾਗੇ ਰਾਮ ਪਿਆਰੇ",
      "norm_target": "snt jnaa raam piaaree",
      "norm_pred": "sdaa jaagee raam piaaree",
      "ratio": 80.0,
      "token_sort_ratio": 80.0,
      "wratio": 80.0,
      "exact_norm": false
    },
    {
      "idx": 3291,
      "audio": "training_data/silver_300h_holdout/clips/SjkbOQTpBv0_clip_00003.wav",
      "video_id": "SjkbOQTpBv0",
      "shabad_id": "SC1",
      "duration_s": 11.08,
      "label_score": 1.0,
      "target": "ਸਾਹਿਬੁ ਮੇਰਾ ਮਿਹਰਵਾਨੁ ਜੀਅ ਸਗਲ ਕਉ ਦੇਇ ਦਾਨੁ",
      "pred": "ਸਾਹਿਬੁ ਮੇਰਾ ਮਿਹਰਵਾਨੁ ਜੀਅ ਸਗਲ ਕਉ ਦੇ ਦਾਨੁ",
      "norm_target": "saahibu meeraa mihrvaanu jiia sgl ku deei daanu",
      "norm_pred": "saahibu meeraa mihrvaanu jiia sgl ku dee daanu",
      "ratio": 98.9247311827957,
      "token_sort_ratio": 98.9247311827957,
      "wratio": 98.9247311827957,
      "exact_norm": false
    },
    {
      "idx": 3583,
      "audio": "training_data/silver_300h_holdout/clips/ZYmyfM8mkTw_clip_00007.wav",
      "video_id": "ZYmyfM8mkTw",
      "shabad_id": "JMP",
      "duration_s": 5.721,
      "label_score": 1.0,
      "target": "ਤੇਰਾ ਕਵਣੁ ਸਰਾਫੁ ਬੁਲਾਵਾ",
      "pred": "ਤੇਰਾ ਕਵਣੁ ਸਰਾਫੁ ਬੁਲਾਵਾ",
      "norm_target": "teeraa kvnnu sraaphu bulaavaa",
      "norm_pred": "teeraa kvnnu sraaphu bulaavaa",
      "ratio": 100.0,
      "token_sort_ratio": 100.0,
      "wratio": 100.0,
      "exact_norm": true
    },
    {
      "idx": 4545,
      "audio": "training_data/silver_300h_holdout/clips/iQAbsSM5FO8_clip_00056.wav",
      "video_id": "iQAbsSM5FO8",
      "shabad_id": "MVN",
      "duration_s": 4.04,
      "label_score": 1.0,
      "target": "ਧਨਿ ਰੁਚ ਇਆ",
      "pred": "ਧਨੁ ਪਰਚਾਇਆ",
      "norm_target": "dhni ruc iaa",
      "norm_pred": "dhnu prcaaiaa",
      "ratio": 72.0,
      "token_sort_ratio": 56.00000000000001,
      "wratio": 72.0,
      "exact_norm": false
    },
    {
      "idx": 4657,
      "audio": "training_data/silver_300h_holdout/clips/lV7e4k8K2q4_clip_00004.wav",
      "video_id": "lV7e4k8K2q4",
      "shabad_id": "5NM",
      "duration_s": 8.961,
      "label_score": 1.0,
      "target": "ਕਰਿ ਉਪਦੇਸੁ ਝਿੜਕੇ ਬਹੁ ਭਾਤੀ",
      "pred": "ਕਰਿ ਉਪਦੇਸੁ ਝਿੜਕੇ ਬਹੁ ਭਾਤੀ",
      "norm_target": "kri updeesu jhirrkee bhu bbaatii",
      "norm_pred": "kri updeesu jhirrkee bhu bbaatii",
      "ratio": 100.0,
      "token_sort_ratio": 100.0,
      "wratio": 100.0,
      "exact_norm": true
    },
    {
      "idx": 5714,
      "audio": "training_data/silver_300h_holdout/clips/pdMFF6A-4Fg_clip_00012.wav",
      "video_id": "pdMFF6A-4Fg",
      "shabad_id": "HYC",
      "duration_s": 6.32,
      "label_score": 1.0,
      "target": "ਸਭੇ ਥੋਕ ਪਰਾਪਤੇ ਜੇ ਆਵੈ ਇਕੁ ਹਥਿ",
      "pred": "ਸਭੇ ਥੋਕ ਪਰਾਪਤੇ ਜੇ ਆਵੈ ਇਕੁ ਹਥਿ",
      "norm_target": "sbbee thook praaptee jee aavai iku hthi",
      "norm_pred": "sbbee thook praaptee jee aavai iku hthi",
      "ratio": 100.0,
      "token_sort_ratio": 100.0,
      "wratio": 100.0,
      "exact_norm": true
    },
    {
      "idx": 6336,
      "audio": "training_data/silver_300h_holdout/clips/srf-mMyyozw_clip_00004.wav",
      "video_id": "srf-mMyyozw",
      "shabad_id": "A0N",
      "duration_s": 9.239,
      "label_score": 1.0,
      "target": "ਸੁਆਮੀ ਮੇਰੈ ਸਰਬ ਕਲਾ ਬਣਿ ਆਈ",
      "pred": "ਸੁਆਮੀ ਮੇਰੈ ਸਰਬ ਕਲਾ ਬਣਿ ਆਈ",
      "norm_target": "suaamii meerai srb klaa bnni aaii",
      "norm_pred": "suaamii meerai srb klaa bnni aaii",
      "ratio": 100.0,
      "token_sort_ratio": 100.0,
      "wratio": 100.0,
      "exact_norm": true
    },
    {
      "idx": 6675,
      "audio": "training_data/silver_300h_holdout/clips/zBX2woljpm8_clip_00007.wav",
      "video_id": "zBX2woljpm8",
      "shabad_id": "DPP",
      "duration_s": 7.681,
      "label_score": 1.0,
      "target": "ਜੇ ਮਿਲੈ ਮੈ ਦਸੇ",
      "pred": "ਜੇ ਮਿਲੈ ਮੈ ਦਸੇ",
      "norm_target": "jee milai mai dsee",
      "norm_pred": "jee milai mai dsee",
      "ratio": 100.0,
      "token_sort_ratio": 100.0,
      "wratio": 100.0,
      "exact_norm": true
    },
    {
      "idx": 6790,
      "audio": "training_data/silver_300h_holdout/clips/0N7ZF7RRKtw_clip_00003.wav",
      "video_id": "0N7ZF7RRKtw",
      "shabad_id": "W2D",
      "duration_s": 9.961,
      "label_score": 1.0,
      "target": "ਵਰੁ ਲੋੜੀਦਾ ਆਇਆ ਵਜੀ ਵਾਧਾਈ",
      "pred": "ਵਰੁ ਲੋੜੀਦਾ ਆਇਆ ਵਜੀ ਵਾਧਾਈ",
      "norm_target": "vru loorriidaa aaiaa vjii vaadhaaii",
      "norm_pred": "vru loorriidaa aaiaa vjii vaadhaaii",
      "ratio": 100.0,
      "token_sort_ratio": 100.0,
      "wratio": 100.0,
      "exact_norm": true
    },
    {
      "idx": 6923,
      "audio": "training_data/silver_300h_holdout/clips/3H8WwqVcUL8_clip_00006.wav",
      "video_id": "3H8WwqVcUL8",
      "shabad_id": "UBH",
      "duration_s": 5.44,
      "label_score": 1.0,
      "target": "ਆਪਿ ਖਲੋਇਆ ਹਰਿ ਕੰਮੁ ਕਰਾਵਣਿ",
      "pred": "ਆਪਿ ਖਲੋਇਆ ਹਰਿ ਕੰਮੁ ਕਰਾਵਣਿ",
      "norm_target": "aapi khlooiaa hri knmu kraavnni",
      "norm_pred": "aapi khlooiaa hri knmu kraavnni",
      "ratio": 100.0,
      "token_sort_ratio": 100.0,
      "wratio": 100.0,
      "exact_norm": true
    },
    {
      "idx": 7609,
      "audio": "training_data/silver_300h_holdout/clips/7WkqVP6buv8_clip_00013.wav",
      "video_id": "7WkqVP6buv8",
      "shabad_id": "1U3",
      "duration_s": 5.4,
      "label_score": 1.0,
      "target": "ਰਖਵਾਲਾ ਗੋਬਿੰਦ ਰਾਇ",
      "pred": "ਰਖਵਾਲਾ ਗੋਬਿੰਦ ਰਾਇ",
      "norm_target": "rkhvaalaa goobind raai",
      "norm_pred": "rkhvaalaa goobind raai",
      "ratio": 100.0,
      "token_sort_ratio": 100.0,
      "wratio": 100.0,
      "exact_norm": true
    },
    {
      "idx": 4,
      "audio": "training_data/silver_300h_holdout/clips/njmuAa8IY80_clip_01683.wav",
      "video_id": "njmuAa8IY80",
      "shabad_id": "7TL",
      "duration_s": 7.281,
      "label_score": 1.0,
      "target": "ਜੇ ਕੋ ਕਰੇ ਚਿਤੁ ਲਾਇ ਜੇ ਕੋ ਕਰੇ",
      "pred": "ਜੇ ਕੋ ਕਰੇ ਚਿਤੁ ਲਾਇ ਜੇ ਕੋ ਕਰੇ",
      "norm_target": "jee koo kree citu laai jee koo kree",
      "norm_pred": "jee koo kree citu laai jee koo kree",
      "ratio": 100.0,
      "token_sort_ratio": 100.0,
      "wratio": 100.0,
      "exact_norm": true
    },
    {
      "idx": 354,
      "audio": "training_data/silver_300h_holdout/clips/rChM6_mmWpQ_clip_00016.wav",
      "video_id": "rChM6_mmWpQ",
      "shabad_id": "R0K",
      "duration_s": 4.72,
      "label_score": 1.0,
      "target": "ਨਾਮੁ ਤੁਮਾਰਾ ਤੇਰੀ ਸਰਣਿ",
      "pred": "ਨਾਮੁ ਤੁਮਾਰਾ ਤੇਰੀ ਸਰਣਿ",
      "norm_target": "naamu tumaaraa teerii srnni",
      "norm_pred": "naamu tumaaraa teerii srnni",
      "ratio": 100.0,
      "token_sort_ratio": 100.0,
      "wratio": 100.0,
      "exact_norm": true
    },
    {
      "idx": 457,
      "audio": "training_data/silver_300h_holdout/clips/1zc7krygelw_clip_00011.wav",
      "video_id": "1zc7krygelw",
      "shabad_id": "JA8",
      "duration_s": 7.32,
      "label_score": 1.0,
      "target": "ਟਾਂਡਾ ਲਾਦਿਆ ਜਾਇ ਰੇ",
      "pred": "ਟਾਂਡਾ ਲਾਗਿਆ ਜਾਇ ਰੇ",
      "norm_target": "ttaanddaa laadiaa jaai ree",
      "norm_pred": "ttaanddaa laagiaa jaai ree",
      "ratio": 96.15384615384616,
      "token_sort_ratio": 96.15384615384616,
      "wratio": 96.15384615384616,
      "exact_norm": false
    },
    {
      "idx": 535,
      "audio": "training_data/silver_300h_holdout/clips/2d_Wy2Vb6n4_clip_00006.wav",
      "video_id": "2d_Wy2Vb6n4",
      "shabad_id": "TA4",
      "duration_s": 7.2,
      "label_score": 1.0,
      "target": "ਥੀਆ ਸੰਤਨ ਬਿਨੁ ਅਵਰੁ ਨ ਦਾਤਾ",
      "pred": "ਪੀਆ ਸੰਤਨ ਬਿਨੁ ਅਗਨਿ ਨ ਦਾਤਾ",
      "norm_target": "thiiaa sntn binu avru n daataa",
      "norm_pred": "piiaa sntn binu agni n daataa",
      "ratio": 84.7457627118644,
      "token_sort_ratio": 67.79661016949152,
      "wratio": 84.7457627118644,
      "exact_norm": false
    },
    {
      "idx": 721,
      "audio": "training_data/silver_300h_holdout/clips/6xbaRKbOhPc_clip_00008.wav",
      "video_id": "6xbaRKbOhPc",
      "shabad_id": "5SV",
      "duration_s": 5.04,
      "label_score": 1.0,
      "target": "ਭਗਤਾ ਕੀ ਟੇਕ ਤੂੰ",
      "pred": "ਭਗਤਾ ਕੀ ਟੇਕ ਤੂੰ",
      "norm_target": "bbgtaa kii tteek tuun",
      "norm_pred": "bbgtaa kii tteek tuun",
      "ratio": 100.0,
      "token_sort_ratio": 100.0,
      "wratio": 100.0,
      "exact_norm": true
    },
    {
      "idx": 894,
      "audio": "training_data/silver_300h_holdout/clips/9NWAGIUkfU4_clip_00024.wav",
      "video_id": "9NWAGIUkfU4",
      "shabad_id": "5BD",
      "duration_s": 15.52,
      "label_score": 0.9230769230769231,
      "target": "ਨਿਰੰਕਾਰੁ ਨਿਰਵੈਰੁ ਅਵਰੁ ਨਹੀ ਦੂਸਰ ਕੋਈ ਭੰਜਨ ਗੜਨ ਸਮਥੁ ਤਰਣ ਤਾਰਣ ਪ੍ਰਭੁ ਸੋਈ",
      "pred": "ਨਿਰੰਕਾਰੁ ਨਿਰਵੈਰੁ ਅਵਰੁ ਨਹੀ ਦੂਸਰ ਕੋਈ ਭੰਜਨ ਗੜਨ ਸਮਥੁ ਤਰਣ ਤਾਰਣ ਪ੍ਰਭੁ ਸੋਈ",
      "norm_target": "nirnkaaru nirvairu avru nhii duusr kooii bbnjn grrn smthu trnn taarnn prbbu sooii",
      "norm_pred": "nirnkaaru nirvairu avru nhii duusr kooii bbnjn grrn smthu trnn taarnn prbbu sooii",
      "ratio": 100.0,
      "token_sort_ratio": 100.0,
      "wratio": 100.0,
      "exact_norm": true
    },
    {
      "idx": 1947,
      "audio": "training_data/silver_300h_holdout/clips/DNm47efW0po_clip_00023.wav",
      "video_id": "DNm47efW0po",
      "shabad_id": "1YU",
      "duration_s": 9.76,
      "label_score": 0.9090909090909091,
      "target": "ਨਾਮ ਬਿਨਾ ਸਭ ਦੁਨੀਆ ਛਾਰੁ ਅਚਰਜੁ ਤੇਰੀ ਕੁਦਰਤਿ ਤੇਰੇ ਕਦਮ ਸਾਲਾ",
      "pred": "ਨਾਮ ਬਿਨਾ ਸਭ ਦੁਨੀਆ ਛਾ ਅਚਰਜੁ ਤੇਰੀ ਕੁਦਰਤਿ ਤੇਰੇ ਕਦਮ ਸਲਾਹ",
      "norm_target": "naam binaa sbb duniiaa chaaru acrju teerii kudrti teeree kdm saalaa",
      "norm_pred": "naam binaa sbb duniiaa chaa acrju teerii kudrti teeree kdm slaah",
      "ratio": 96.18320610687023,
      "token_sort_ratio": 90.07633587786259,
      "wratio": 96.18320610687023,
      "exact_norm": false
    },
    {
      "idx": 2886,
      "audio": "training_data/silver_300h_holdout/clips/HJ9h97PeRto_clip_00006.wav",
      "video_id": "HJ9h97PeRto",
      "shabad_id": "TDH",
      "duration_s": 5.761,
      "label_score": 1.0,
      "target": "ਗੁਰ ਦੇਖੇ ਨੀਦ ਨ ਆਵੈ",
      "pred": "ਗੁਰ ਦੇਖੇ ਨੀਦ ਨ ਆਵੈ",
      "norm_target": "gur deekhee niid n aavai",
      "norm_pred": "gur deekhee niid n aavai",
      "ratio": 100.0,
      "token_sort_ratio": 100.0,
      "wratio": 100.0,
      "exact_norm": true
    },
    {
      "idx": 3237,
      "audio": "training_data/silver_300h_holdout/clips/PYUPZn6wiR8_clip_00021.wav",
      "video_id": "PYUPZn6wiR8",
      "shabad_id": "VGA",
      "duration_s": 7.8,
      "label_score": 1.0,
      "target": "ਸੰਤ ਜਨਾ ਰਾਮ ਪਿਆਰੇ",
      "pred": "ਸਦਾ ਜਾਗੇ ਰਾਮ ਪਿਆਰੇ",
      "norm_target": "snt jnaa raam piaaree",
      "norm_pred": "sdaa jaagee raam piaaree",
      "ratio": 80.0,
      "token_sort_ratio": 80.0,
      "wratio": 80.0,
      "exact_norm": false
    },
    {
      "idx": 3292,
      "audio": "training_data/silver_300h_holdout/clips/SjkbOQTpBv0_clip_00006.wav",
      "video_id": "SjkbOQTpBv0",
      "shabad_id": "SC1",
      "duration_s": 10.921,
      "label_score": 1.0,
      "target": "ਸਾਹਿਬੁ ਮਿਹਰਵਾਨੁ ਸਾਹਿਬੁ ਮੇਰਾ ਮਿਹਰਵਾਨੁ",
      "pred": "ਸਾਹਿਬੁ ਮਿਹਰਵਾਨੁ ਸਾਹਿਬੁ ਮੇਰਾ ਮਿਹਰਵਾਨੁ",
      "norm_target": "saahibu mihrvaanu saahibu meeraa mihrvaanu",
      "norm_pred": "saahibu mihrvaanu saahibu meeraa mihrvaanu",
      "ratio": 100.0,
      "token_sort_ratio": 100.0,
      "wratio": 100.0,
      "exact_norm": true
    },
    {
      "idx": 3584,
      "audio": "training_data/silver_300h_holdout/clips/ZYmyfM8mkTw_clip_00008.wav",
      "video_id": "ZYmyfM8mkTw",
      "shabad_id": "JMP",
      "duration_s": 5.8,
      "label_score": 1.0,
      "target": "ਤੇਰਾ ਕਵਣੁ ਸਰਾਫੁ ਬੁਲਾਵਾ",
      "pred": "ਤੇਰਾ ਕਵਣੁ ਸਰਾਫੁ ਬੁਲਾਵਾ",
      "norm_target": "teeraa kvnnu sraaphu bulaavaa",
      "norm_pred": "teeraa kvnnu sraaphu bulaavaa",
      "ratio": 100.0,
      "token_sort_ratio": 100.0,
      "wratio": 100.0,
      "exact_norm": true
    },
    {
      "idx": 4546,
      "audio": "training_data/silver_300h_holdout/clips/iQAbsSM5FO8_clip_00059.wav",
      "video_id": "iQAbsSM5FO8",
      "shabad_id": "MVN",
      "duration_s": 4.12,
      "label_score": 1.0,
      "target": "ਧਨਿ ਰੁਚ ਇਆ",
      "pred": "ਮਨਿ ਪਰਚਾਇਆ",
      "norm_target": "dhni ruc iaa",
      "norm_pred": "mni prcaaiaa",
      "ratio": 66.66666666666667,
      "token_sort_ratio": 50.0,
      "wratio": 66.66666666666667,
      "exact_norm": false
    },
    {
      "idx": 4658,
      "audio": "training_data/silver_300h_holdout/clips/lV7e4k8K2q4_clip_00007.wav",
      "video_id": "lV7e4k8K2q4",
      "shabad_id": "5NM",
      "duration_s": 7.6,
      "label_score": 1.0,
      "target": "ਪਿਛਲੇ ਅਉਗੁਣ ਬਖਸਿ ਲਏ ਪ੍ਰਭੁ",
      "pred": "ਪਿਛਲੇ ਅਗਣ ਬਖਸਿ ਲਏ ਪ੍ਰਭੁ",
      "norm_target": "pichlee augunn bkhsi lee prbbu",
      "norm_pred": "pichlee agnn bkhsi lee prbbu",
      "ratio": 96.55172413793103,
      "token_sort_ratio": 96.55172413793103,
      "wratio": 96.55172413793103,
      "exact_norm": false
    },
    {
      "idx": 5715,
      "audio": "training_data/silver_300h_holdout/clips/pdMFF6A-4Fg_clip_00013.wav",
      "video_id": "pdMFF6A-4Fg",
      "shabad_id": "HYC",
      "duration_s": 6.88,
      "label_score": 1.0,
      "target": "ਜਨਮੁ ਪਦਾਰਥੁ ਸਫਲੁ ਹੈ ਜੇ ਸਚਾ ਸਬਦੁ ਕਥਿ",
      "pred": "ਜਨਮੁ ਪਦਾਰਥੁ ਸਫਲੁ ਹੈ ਜੇ ਸਚਾ ਸਬਦੁ ਕਥਿ",
      "norm_target": "jnmu pdaarthu sphlu hai jee scaa sbdu kthi",
      "norm_pred": "jnmu pdaarthu sphlu hai jee scaa sbdu kthi",
      "ratio": 100.0,
      "token_sort_ratio": 100.0,
      "wratio": 100.0,
      "exact_norm": true
    },
    {
      "idx": 6337,
      "audio": "training_data/silver_300h_holdout/clips/srf-mMyyozw_clip_00006.wav",
      "video_id": "srf-mMyyozw",
      "shabad_id": "A0N",
      "duration_s": 6.8,
      "label_score": 1.0,
      "target": "ਪ੍ਰਗਟ ਭਈ ਸਗਲੇ ਜੁਗ ਅੰਤਰਿ",
      "pred": "ਪ੍ਰਗਟ ਭਈ ਸਗਲੇ ਜੁਗ ਅੰਤਰਿ",
      "norm_target": "prgtt bbii sglee jug antri",
      "norm_pred": "prgtt bbii sglee jug antri",
      "ratio": 100.0,
      "token_sort_ratio": 100.0,
      "wratio": 100.0,
      "exact_norm": true
    },
    {
      "idx": 6676,
      "audio": "training_data/silver_300h_holdout/clips/zBX2woljpm8_clip_00008.wav",
      "video_id": "zBX2woljpm8",
      "shabad_id": "DPP",
      "duration_s": 6.039,
      "label_score": 1.0,
      "target": "ਪ੍ਰਭੁ ਗੁਣਤਾਸੁ",
      "pred": "ਪ੍ਰਭੁ ਗੁਣਤਾਸੁ",
      "norm_target": "prbbu gunntaasu",
      "norm_pred": "prbbu gunntaasu",
      "ratio": 100.0,
      "token_sort_ratio": 100.0,
      "wratio": 100.0,
      "exact_norm": true
    },
    {
      "idx": 6791,
      "audio": "training_data/silver_300h_holdout/clips/0N7ZF7RRKtw_clip_00005.wav",
      "video_id": "0N7ZF7RRKtw",
      "shabad_id": "NB5",
      "duration_s": 5.0,
      "label_score": 1.0,
      "target": "ਮਨਿ ਵਾਧਾਈਆ",
      "pred": "ਮਨਿ ਵਾਧਾਈਆ",
      "norm_target": "mni vaadhaaiiaa",
      "norm_pred": "mni vaadhaaiiaa",
      "ratio": 100.0,
      "token_sort_ratio": 100.0,
      "wratio": 100.0,
      "exact_norm": true
    },
    {
      "idx": 6924,
      "audio": "training_data/silver_300h_holdout/clips/3H8WwqVcUL8_clip_00007.wav",
      "video_id": "3H8WwqVcUL8",
      "shabad_id": "UBH",
      "duration_s": 4.52,
      "label_score": 1.0,
      "target": "ਆਇਆ ਰਾਮ",
      "pred": "ਆਇਆ ਰਾਮ",
      "norm_target": "aaiaa raam",
      "norm_pred": "aaiaa raam",
      "ratio": 100.0,
      "token_sort_ratio": 100.0,
      "wratio": 100.0,
      "exact_norm": true
    },
    {
      "idx": 7610,
      "audio": "training_data/silver_300h_holdout/clips/7WkqVP6buv8_clip_00014.wav",
      "video_id": "7WkqVP6buv8",
      "shabad_id": "1U3",
      "duration_s": 6.359,
      "label_score": 1.0,
      "target": "ਸਿਮਰਿ ਸਿਮਰਿ ਪੂਰਨ ਪ੍ਰਭੂ",
      "pred": "ਸਿਮਰਿ ਸਿਮਰਿ ਪੂਰਨ ਪ੍ਰਭੂ",
      "norm_target": "simri simri puurn prbbuu",
      "norm_pred": "simri simri puurn prbbuu",
      "ratio": 100.0,
      "token_sort_ratio": 100.0,
      "wratio": 100.0,
      "exact_norm": true
    },
    {
      "idx": 5,
      "audio": "training_data/silver_300h_holdout/clips/njmuAa8IY80_clip_01687.wav",
      "video_id": "njmuAa8IY80",
      "shabad_id": "E3S",
      "duration_s": 6.08,
      "label_score": 1.0,
      "target": "ਕੁਦਰਤਿ ਕੇ ਸਭ ਬੰਦੇ",
      "pred": "ਕੁਦਰਤਿ ਕੇ ਸਭ ਬੰਦੇ",
      "norm_target": "kudrti kee sbb bndee",
      "norm_pred": "kudrti kee sbb bndee",
      "ratio": 100.0,
      "token_sort_ratio": 100.0,
      "wratio": 100.0,
      "exact_norm": true
    },
    {
      "idx": 355,
      "audio": "training_data/silver_300h_holdout/clips/rChM6_mmWpQ_clip_00017.wav",
      "video_id": "rChM6_mmWpQ",
      "shabad_id": "R0K",
      "duration_s": 10.417,
      "label_score": 1.0,
      "target": "ਸਤਿਗੁਰ ਮੇਰੇ ਪੂਰੇ ਤੇਰੀ ਸਰਣਿ ਸਤਿਗੁਰ ਮੇਰੇ ਪੂਰੇ",
      "pred": "ਸਤਿਗੁਰ ਮੇਰੇ ਪੂਰੇ ਤੇਰੀ ਸਰਣਿ ਸਤਿਗੁਰ ਮੇਰੇ ਪੂਰੇ",
      "norm_target": "stigur meeree puuree teerii srnni stigur meeree puuree",
      "norm_pred": "stigur meeree puuree teerii srnni stigur meeree puuree",
      "ratio": 100.0,
      "token_sort_ratio": 100.0,
      "wratio": 100.0,
      "exact_norm": true
    },
    {
      "idx": 458,
      "audio": "training_data/silver_300h_holdout/clips/1zc7krygelw_clip_00013.wav",
      "video_id": "1zc7krygelw",
      "shabad_id": "JA8",
      "duration_s": 8.759,
      "label_score": 1.0,
      "target": "ਮੇਰਾ ਟਾਂਡਾ ਲਾਦਿਆ ਜਾਇ ਰੇ",
      "pred": "ਮੇਰਾ ਟਾਂਡਾ ਲਾਦਿਆ ਜਾਇ ਰੇ",
      "norm_target": "meeraa ttaanddaa laadiaa jaai ree",
      "norm_pred": "meeraa ttaanddaa laadiaa jaai ree",
      "ratio": 100.0,
      "token_sort_ratio": 100.0,
      "wratio": 100.0,
      "exact_norm": true
    },
    {
      "idx": 536,
      "audio": "training_data/silver_300h_holdout/clips/2d_Wy2Vb6n4_clip_00007.wav",
      "video_id": "2d_Wy2Vb6n4",
      "shabad_id": "TA4",
      "duration_s": 6.319,
      "label_score": 1.0,
      "target": "ਬੀਆ ਜੋ ਜੋ ਸਰਣਿ ਪਰੈ",
      "pred": "ਜੀਆ ਜੋ ਜੋ ਸਰਣਿ ਪਰੈ",
      "norm_target": "biiaa joo joo srnni prai",
      "norm_pred": "jiiaa joo joo srnni prai",
      "ratio": 95.83333333333334,
      "token_sort_ratio": 95.83333333333334,
      "wratio": 95.83333333333334,
      "exact_norm": false
    },
    {
      "idx": 722,
      "audio": "training_data/silver_300h_holdout/clips/6xbaRKbOhPc_clip_00009.wav",
      "video_id": "6xbaRKbOhPc",
      "shabad_id": "5SV",
      "duration_s": 7.52,
      "label_score": 1.0,
      "target": "ਸੰਤਾ ਕੀ ਓਟ ਤੂੰ ਸਚਾ",
      "pred": "ਸੰਤਾ ਕੀ ਓਟ ਤੂੰ ਸਚਾ",
      "norm_target": "sntaa kii oott tuun scaa",
      "norm_pred": "sntaa kii oott tuun scaa",
      "ratio": 100.0,
      "token_sort_ratio": 100.0,
      "wratio": 100.0,
      "exact_norm": true
    }
  ]
}